README.rst
resynclinkdest.py
setup.py
resynclinkdest.egg-info/PKG-INFO
resynclinkdest.egg-info/SOURCES.txt
resynclinkdest.egg-info/dependency_links.txt
resynclinkdest.egg-info/entry_points.txt
resynclinkdest.egg-info/top_level.txt
resynclinkdest.egg-info/zip-safe