Metadata-Version: 1.1
Name: resynclinkdest
Version: 1.0.1
Summary: Re-hardlink directories created using ``rsync --link-dest``.
Home-page: http://github.com/vpelletier/resynclinkdest
Author: Vincent Pelletier
Author-email: plr.vincent@gmail.com
License: GPL 3+
Keywords: rsync --link-dest hardlink
Platform: any
Classifier: Intended Audience :: System Administrators
Classifier: License :: OSI Approved :: GNU General Public License v3 or later (GPLv3+)
Classifier: Operating System :: POSIX :: Linux
Classifier: Programming Language :: Python :: 2.7
Classifier: Programming Language :: Python :: 3
Classifier: Programming Language :: Python :: Implementation :: PyPy
Classifier: Programming Language :: Python :: Implementation :: CPython
Classifier: Topic :: System :: Archiving :: Backup
